thoth/python/__init__.py
thoth/python/aiosource.py
thoth/python/artifact.py
thoth/python/configuration.py
thoth/python/constraints.py
thoth/python/digests_fetcher.py
thoth/python/exceptions.py
thoth/python/helpers.py
thoth/python/package_version.py
thoth/python/packages.py
thoth/python/pipfile.py
thoth/python/project.py
thoth/python/source.py
thoth_python-0.17.0.dist-info/LICENSE
thoth_python-0.17.0.dist-info/METADATA
thoth_python-0.17.0.dist-info/WHEEL
thoth_python-0.17.0.dist-info/top_level.txt
thoth_python-0.17.0.dist-info/RECORD
