Metadata-Version: 2.1
Name: thoth-python
Version: 0.17.0
Summary: A Python ecosystem specific library
Author-email: Fridolin Pokorny <fridolin@redhat.com>
License:                     GNU GENERAL PUBLIC LICENSE
Project-URL: Documentation, https://github.com/thoth-station/python
Project-URL: Source, https://github.com/thoth-station/python
Keywords: python,dependency,pypi,dependencies,tool,library,thoth
Classifier: Development Status :: 4 - Beta
Classifier: Programming Language :: Python :: 3
Classifier: Programming Language :: Python :: 3.4
Classifier: Programming Language :: Python :: 3.5
Classifier: Programming Language :: Python :: 3.6
Classifier: Environment :: Console
Classifier: Intended Audience :: Developers
Classifier: Operating System :: OS Independent
Classifier: Programming Language :: Python :: Implementation :: CPython
Classifier: License :: OSI Approved :: GNU General Public License v3 or later (GPLv3+)
License-File: LICENSE
